README.md
setup.py
pulumi_supabase/__init__.py
pulumi_supabase/_enums.py
pulumi_supabase/_utilities.py
pulumi_supabase/function.py
pulumi_supabase/get_type_script.py
pulumi_supabase/organization.py
pulumi_supabase/project.py
pulumi_supabase/provider.py
pulumi_supabase/pulumi-plugin.json
pulumi_supabase/py.typed
pulumi_supabase/secret.py
pulumi_supabase.egg-info/PKG-INFO
pulumi_supabase.egg-info/SOURCES.txt
pulumi_supabase.egg-info/dependency_links.txt
pulumi_supabase.egg-info/not-zip-safe
pulumi_supabase.egg-info/requires.txt
pulumi_supabase.egg-info/top_level.txt
pulumi_supabase/config/__init__.py
pulumi_supabase/config/vars.py