Metadata-Version: 2.1
Name: pulumi-supabase
Version: 1.1.1
Summary: UNKNOWN
Home-page: UNKNOWN
License: UNKNOWN
Platform: UNKNOWN
